mascope_sdk/__init__.py
mascope_sdk-2025.10.14.dist-info/WHEEL
mascope_sdk-2025.10.14.dist-info/METADATA
mascope_sdk-2025.10.14.dist-info/RECORD
