Metadata-Version: 2.3
Name: mascope-sdk
Version: 2025.10.14
Summary: Mascope's public SDK library, wrapping the app's REST API.
Author: Oskari Kausiala, Philip Chernonog
Author-email: Oskari Kausiala <oskari.kausiala@karsa.fi>>, Philip Chernonog <philip.chernonog@karsa.fi>>
License: MIT
Classifier: Topic :: Scientific/Engineering :: Atmospheric Science
Classifier: Topic :: Software Development :: Libraries :: Python Modules
Requires-Dist: requests>=2.32.3
Requires-Dist: loguru>=0.7.3
Maintainer: Oskari Kausiala, Philip Chernonog
Maintainer-email: Oskari Kausiala <oskari.kausiala@karsa.fi>>, Philip Chernonog <philip.chernonog@karsa.fi>>
Requires-Python: >=3.10
Project-URL: Bug Tracker, https://github.com/Karsa-Oy/Mascope/issues
Project-URL: documentation, https://github.com/Karsa-Oy/Mascope
Project-URL: homepage, https://karsa.fi/
Project-URL: repository, https://github.com/Karsa-Oy/Mascope
